evg_task_profiler_py-0.2.0.dist-info/METADATA
evg_task_profiler_py-0.2.0.dist-info/WHEEL
evg_task_profiler_py/__init__.py
evg_task_profiler_py/evg_task_profiler_py.cpython-310-darwin.so
evg_task_profiler_py-0.2.0.dist-info/RECORD
