Metadata-Version: 2.1
Name: evg-task-profiler-py
Version: 0.2.0
Classifier: Programming Language :: Rust
Classifier: Programming Language :: Python :: Implementation :: CPython
Classifier: Programming Language :: Python :: Implementation :: PyPy
Author-email: David Bradford <david.bradford@mongodb.com>
Requires-Python: >=3.7
Project-URL: homepage, https://github.com/dbradf/evg-task-profiler.py
Project-URL: repository, https://github.com/dbradf/evg-task-profiler.py
